Workbook
Name accounts: Accounts!$A$1:$G$86
Name products: Products!$A$1:$C$8
Name sales_pipeline: Sales_Pipelines!$A$1:$H$8801
Name sales_teams: Sales_teams!$A$1:$C$36

Sheet Analysis
A1: CRM Sales Performance Analysis
A2: B2B Sales Pipeline & Performance Overview | 2017
A4: Won Revenue | B4: =SUM(Sales_Pipelines!H3:H8802) -> 10004480 | C4: Open Pipeline | D4: =SUM(Sales_Pipelines!L2:L8801) -> 85895 | E4: Open Opportunities | F4: =B5 -> 2089 | G4: Avg. Opportunity Value | H4: =B6 -> 2377.3169
A5: Open Opportunities | B5: =COUNTIFS(Sales_Pipelines!E2:E8801,"Prospecting")+COUNTIFS(Sales_Pipelines!E2:E8801,"Engaging") -> 2089
A6: Avg. Open Opportunity Value | B6: =AVERAGEIFS(Sales_Pipelines!J2:J8801,Sales_Pipelines!E2:E8801,"<>Won",Sales_Pipelines!E2:E8801,"<>Lost") -> 2377.3169
A7: Estimated Lost Value (Proxy) | B7: =SUMPRODUCT((Sales_Pipelines!E2:E8801="Lost")*VLOOKUP(Sales_Pipelines!C2:C8801,Products!$A$2:$C$8,3,FALSE)) -> 136015
A9: Deal Stage Performance | E9: Top Sales Agents
A10: Deal Stage | B10: Opportunities | C10: Percentage | E10: Sales Agent | F10: Won Revenue
A11: Prospecting | B11: =COUNTIF(Sales_Pipelines!$E$2:$E$8801,A11) -> 500 | C11: =B11/SUM($B$11:$B$14) -> 0.056818182 | E11: =INDEX(A29:A63,MATCH(F11,B29:B63,0)) -> Darcel Schlecht | F11: =MAX(B32:B66) -> 1153214
A12: Engaging | B12: =COUNTIF(Sales_Pipelines!$E$2:$E$8801,A12) -> 1589 | C12: =B12/SUM($B$11:$B$14) -> 0.18056818 | E12: =INDEX(A32:A66,MATCH(F12,B32:B66,0)) -> Vicki Laflamme | F12: =LARGE(B32:B66,2) -> 478396
A13: Won | B13: =COUNTIF(Sales_Pipelines!$E$2:$E$8801,"Won") -> 4238 | C13: =B13/SUM($B$11:$B$14) -> 0.48159091 | E13: =INDEX(A32:A66,MATCH(F13,B32:B66,0)) -> Kary Hendrixson | F13: =LARGE(B32:B66,3) -> 454298
A14: Lost | B14: =COUNTIF(Sales_Pipelines!$E$2:$E$8801,A14) -> 2473 | C14: =B14/SUM($B$11:$B$14) -> 0.28102273 | E14: =INDEX(A32:A66,MATCH(F14,B32:B66,0)) -> Cassey Cress | F14: =LARGE(B32:B66,4) -> 450489
A15: Closed Win Rate | B15: =COUNTIF(Sales_Pipelines!E2:E8801,"Won")/(COUNTIF(Sales_Pipelines!E2:E8801,"Won")+COUNTIF(Sales_Pipelines!E2:E8801,"Lost")) -> 0.63150052 | E15: =INDEX(A32:A66,MATCH(F15,B32:B66,0)) -> Donn Cantrell | F15: =LARGE(B32:B66,5) -> 445860
A16: Average Won Deal Value | B16: =AVERAGEIFS(Sales_Pipelines!H2:H8801,Sales_Pipelines!E2:E8801,"Won") -> 2360.9094 | E16: =INDEX(A32:A66,MATCH(F16,B32:B66,0)) -> Reed Clapper | F16: =LARGE(B32:B66,6) -> 438336
A19: Product Performance
A20: Product | B20: Won Revenue | C20: Won Opportunities | D20: Total Opportunities | E20: Win Rate | F20: Average Won Deal Value | G20: Estimated Lost Value
A21: GTX Basic | B21: =SUMIFS(Sales_Pipelines!$H$2:$H$8801,Sales_Pipelines!$C$2:$C$8801,A21,Sales_Pipelines!$E$2:$E$8801,"Won") -> 499263 | C21: =COUNTIFS(Sales_Pipelines!$C$2:$C$8801,A21,Sales_Pipelines!$E$2:$E$8801,"Won") -> 915 | D21: =COUNTIF(Sales_Pipelines!$C$2:$C$8801,A21) -> 1866 | E21: =C21/D21 -> 0.4903537 | F21: =IF(C21=0,0,B21/C21) -> 545.64262 | G21: =COUNTIFS(Sales_Pipelines!$C$2:$C$8801,A21,Sales_Pipelines!$E$2:$E$8801,"Lost")*VLOOKUP(A21,Products!$A$2:$C$8,3,FALSE) -> 286550
A22: GTX Pro | B22: =SUMIFS(Sales_Pipelines!$H$2:$H$8801,Sales_Pipelines!$C$2:$C$8801,A22,Sales_Pipelines!$E$2:$E$8801,"Won") -> 3510578 | C22: =COUNTIFS(Sales_Pipelines!$C$2:$C$8801,A22,Sales_Pipelines!$E$2:$E$8801,"Won") -> 729 | D22: =COUNTIF(Sales_Pipelines!$C$2:$C$8801,A22) -> 1480 | E22: =C22/D22 -> 0.49256757 | F22: =IF(C22=0,0,B22/C22) -> 4815.6077 | G22: =COUNTIFS(Sales_Pipelines!$C$2:$C$8801,A22,Sales_Pipelines!$E$2:$E$8801,"Lost")*VLOOKUP(A22,Products!$A$2:$C$8,3,FALSE) -> 2015178
A23: MG Special | B23: =SUMIFS(Sales_Pipelines!$H$2:$H$8801,Sales_Pipelines!$C$2:$C$8801,A23,Sales_Pipelines!$E$2:$E$8801,"Won") -> 43768 | C23: =COUNTIFS(Sales_Pipelines!$C$2:$C$8801,A23,Sales_Pipelines!$E$2:$E$8801,"Won") -> 793 | D23: =COUNTIF(Sales_Pipelines!$C$2:$C$8801,A23) -> 1651 | E23: =C23/D23 -> 0.48031496 | F23: =IF(C23=0,0,B23/C23) -> 55.192938 | G23: =COUNTIFS(Sales_Pipelines!$C$2:$C$8801,A23,Sales_Pipelines!$E$2:$E$8801,"Lost")*VLOOKUP(A23,Products!$A$2:$C$8,3,FALSE) -> 23650
A24: MG Advanced | B24: =SUMIFS(Sales_Pipelines!$H$2:$H$8801,Sales_Pipelines!$C$2:$C$8801,A24,Sales_Pipelines!$E$2:$E$8801,"Won") -> 2216387 | C24: =COUNTIFS(Sales_Pipelines!$C$2:$C$8801,A24,Sales_Pipelines!$E$2:$E$8801,"Won") -> 654 | D24: =COUNTIF(Sales_Pipelines!$C$2:$C$8801,A24) -> 1412 | E24: =C24/D24 -> 0.4631728 | F24: =IF(C24=0,0,B24/C24) -> 3388.9709 | G24: =COUNTIFS(Sales_Pipelines!$C$2:$C$8801,A24,Sales_Pipelines!$E$2:$E$8801,"Lost")*VLOOKUP(A24,Products!$A$2:$C$8,3,FALSE) -> 1458990
A25: GTX Plus Pro | B25: =SUMIFS(Sales_Pipelines!$H$2:$H$8801,Sales_Pipelines!$C$2:$C$8801,A25,Sales_Pipelines!$E$2:$E$8801,"Won") -> 2629651 | C25: =COUNTIFS(Sales_Pipelines!$C$2:$C$8801,A25,Sales_Pipelines!$E$2:$E$8801,"Won") -> 479 | D25: =COUNTIF(Sales_Pipelines!$C$2:$C$8801,A25) -> 968 | E25: =C25/D25 -> 0.49483471 | F25: =IF(C25=0,0,B25/C25) -> 5489.8768 | G25: =COUNTIFS(Sales_Pipelines!$C$2:$C$8801,A25,Sales_Pipelines!$E$2:$E$8801,"Lost")*VLOOKUP(A25,Products!$A$2:$C$8,3,FALSE) -> 1458212
A26: GTX Plus Basic | B26: =SUMIFS(Sales_Pipelines!$H$2:$H$8801,Sales_Pipelines!$C$2:$C$8801,A26,Sales_Pipelines!$E$2:$E$8801,"Won") -> 705275 | C26: =COUNTIFS(Sales_Pipelines!$C$2:$C$8801,A26,Sales_Pipelines!$E$2:$E$8801,"Won") -> 653 | D26: =COUNTIF(Sales_Pipelines!$C$2:$C$8801,A26) -> 1383 | E26: =C26/D26 -> 0.47216197 | F26: =IF(C26=0,0,B26/C26) -> 1080.0536 | G26: =COUNTIFS(Sales_Pipelines!$C$2:$C$8801,A26,Sales_Pipelines!$E$2:$E$8801,"Lost")*VLOOKUP(A26,Products!$A$2:$C$8,3,FALSE) -> 436208
A27: GTK 500 | B27: =SUMIFS(Sales_Pipelines!$H$2:$H$8801,Sales_Pipelines!$C$2:$C$8801,A27,Sales_Pipelines!$E$2:$E$8801,"Won") -> 400612 | C27: =COUNTIFS(Sales_Pipelines!$C$2:$C$8801,A27,Sales_Pipelines!$E$2:$E$8801,"Won") -> 15 | D27: =COUNTIF(Sales_Pipelines!$C$2:$C$8801,A27) -> 40 | E27: =C27/D27 -> 0.375 | F27: =IF(C27=0,0,B27/C27) -> 26707.467 | G27: =COUNTIFS(Sales_Pipelines!$C$2:$C$8801,A27,Sales_Pipelines!$E$2:$E$8801,"Lost")*VLOOKUP(A27,Products!$A$2:$C$8,3,FALSE) -> 267680
A30: Sales Agent Performance
A31: Sales Agent | B31: Won Revenue | C31: Won Opportunities | D31: Total Opportunities | E31: Win Rate | F31: Won Deal Value | G31: Manager | H31: Regional Office
A32: Anna Snelling | B32: =SUMIFS(Sales_Pipelines!$H$2:$H$8801,Sales_Pipelines!$B$2:$B$8801,A32,Sales_Pipelines!$E$2:$E$8801,"Won") -> 275056 | C32: =COUNTIFS(Sales_Pipelines!$B$2:$B$8801,A32,Sales_Pipelines!$E$2:$E$8801,"Won") -> 208 | D32: =COUNTIF(Sales_Pipelines!$B$2:$B$8801,A32) -> 448 | E32: =IF(D32=0,0,C32/D32) -> 0.46428571 | F32: =IF(C32=0,0,B32/C32) -> 1322.3846 | G32: =VLOOKUP(A32,Sales_teams!$A$2:$C$36,2,FALSE) -> Dustin Brinkmann | H32: =VLOOKUP(A32,Sales_teams!$A$2:$C$36,3,FALSE) -> Central
A33: Cecily Lampkin | B33: =SUMIFS(Sales_Pipelines!$H$2:$H$8801,Sales_Pipelines!$B$2:$B$8801,A33,Sales_Pipelines!$E$2:$E$8801,"Won") -> 229800 | C33: =COUNTIFS(Sales_Pipelines!$B$2:$B$8801,A33,Sales_Pipelines!$E$2:$E$8801,"Won") -> 107 | D33: =COUNTIF(Sales_Pipelines!$B$2:$B$8801,A33) -> 203 | E33: =IF(D33=0,0,C33/D33) -> 0.5270936 | F33: =IF(C33=0,0,B33/C33) -> 2147.6636 | G33: =VLOOKUP(A33,Sales_teams!$A$2:$C$36,2,FALSE) -> Dustin Brinkmann | H33: =VLOOKUP(A33,Sales_teams!$A$2:$C$36,3,FALSE) -> Central
A34: Versie Hillebrand | B34: =SUMIFS(Sales_Pipelines!$H$2:$H$8801,Sales_Pipelines!$B$2:$B$8801,A34,Sales_Pipelines!$E$2:$E$8801,"Won") -> 187693 | C34: =COUNTIFS(Sales_Pipelines!$B$2:$B$8801,A34,Sales_Pipelines!$E$2:$E$8801,"Won") -> 176 | D34: =COUNTIF(Sales_Pipelines!$B$2:$B$8801,A34) -> 361 | E34: =IF(D34=0,0,C34/D34) -> 0.48753463 | F34: =IF(C34=0,0,B34/C34) -> 1066.4375 | G34: =VLOOKUP(A34,Sales_teams!$A$2:$C$36,2,FALSE) -> Dustin Brinkmann | H34: =VLOOKUP(A34,Sales_teams!$A$2:$C$36,3,FALSE) -> Central
A35: Lajuana Vencill | B35: =SUMIFS(Sales_Pipelines!$H$2:$H$8801,Sales_Pipelines!$B$2:$B$8801,A35,Sales_Pipelines!$E$2:$E$8801,"Won") -> 194632 | C35: =COUNTIFS(Sales_Pipelines!$B$2:$B$8801,A35,Sales_Pipelines!$E$2:$E$8801,"Won") -> 127 | D35: =COUNTIF(Sales_Pipelines!$B$2:$B$8801,A35) -> 311 | E35: =IF(D35=0,0,C35/D35) -> 0.40836013 | F35: =IF(C35=0,0,B35/C35) -> 1532.5354 | G35: =VLOOKUP(A35,Sales_teams!$A$2:$C$36,2,FALSE) -> Dustin Brinkmann | H35: =VLOOKUP(A35,Sales_teams!$A$2:$C$36,3,FALSE) -> Central
A36: Moses Frase | B36: =SUMIFS(Sales_Pipelines!$H$2:$H$8801,Sales_Pipelines!$B$2:$B$8801,A36,Sales_Pipelines!$E$2:$E$8801,"Won") -> 207182 | C36: =COUNTIFS(Sales_Pipelines!$B$2:$B$8801,A36,Sales_Pipelines!$E$2:$E$8801,"Won") -> 129 | D36: =COUNTIF(Sales_Pipelines!$B$2:$B$8801,A36) -> 260 | E36: =IF(D36=0,0,C36/D36) -> 0.49615385 | F36: =IF(C36=0,0,B36/C36) -> 1606.062 | G36: =VLOOKUP(A36,Sales_teams!$A$2:$C$36,2,FALSE) -> Dustin Brinkmann | H36: =VLOOKUP(A36,Sales_teams!$A$2:$C$36,3,FALSE) -> Central
A37: Jonathan Berthelot | B37: =SUMIFS(Sales_Pipelines!$H$2:$H$8801,Sales_Pipelines!$B$2:$B$8801,A37,Sales_Pipelines!$E$2:$E$8801,"Won") -> 284886 | C37: =COUNTIFS(Sales_Pipelines!$B$2:$B$8801,A37,Sales_Pipelines!$E$2:$E$8801,"Won") -> 171 | D37: =COUNTIF(Sales_Pipelines!$B$2:$B$8801,A37) -> 345 | E37: =IF(D37=0,0,C37/D37) -> 0.49565217 | F37: =IF(C37=0,0,B37/C37) -> 1666 | G37: =VLOOKUP(A37,Sales_teams!$A$2:$C$36,2,FALSE) -> Melvin Marxen | H37: =VLOOKUP(A37,Sales_teams!$A$2:$C$36,3,FALSE) -> Central
A38: Marty Freudenburg | B38: =SUMIFS(Sales_Pipelines!$H$2:$H$8801,Sales_Pipelines!$B$2:$B$8801,A38,Sales_Pipelines!$E$2:$E$8801,"Won") -> 291195 | C38: =COUNTIFS(Sales_Pipelines!$B$2:$B$8801,A38,Sales_Pipelines!$E$2:$E$8801,"Won") -> 122 | D38: =COUNTIF(Sales_Pipelines!$B$2:$B$8801,A38) -> 281 | E38: =IF(D38=0,0,C38/D38) -> 0.4341637 | F38: =IF(C38=0,0,B38/C38) -> 2386.8443 | G38: =VLOOKUP(A38,Sales_teams!$A$2:$C$36,2,FALSE) -> Melvin Marxen | H38: =VLOOKUP(A38,Sales_teams!$A$2:$C$36,3,FALSE) -> Central
A39: Gladys Colclough | B39: =SUMIFS(Sales_Pipelines!$H$2:$H$8801,Sales_Pipelines!$B$2:$B$8801,A39,Sales_Pipelines!$E$2:$E$8801,"Won") -> 345674 | C39: =COUNTIFS(Sales_Pipelines!$B$2:$B$8801,A39,Sales_Pipelines!$E$2:$E$8801,"Won") -> 135 | D39: =COUNTIF(Sales_Pipelines!$B$2:$B$8801,A39) -> 317 | E39: =IF(D39=0,0,C39/D39) -> 0.42586751 | F39: =IF(C39=0,0,B39/C39) -> 2560.5481 | G39: =VLOOKUP(A39,Sales_teams!$A$2:$C$36,2,FALSE) -> Melvin Marxen | H39: =VLOOKUP(A39,Sales_teams!$A$2:$C$36,3,FALSE) -> Central
A40: Niesha Huffines | B40: =SUMIFS(Sales_Pipelines!$H$2:$H$8801,Sales_Pipelines!$B$2:$B$8801,A40,Sales_Pipelines!$E$2:$E$8801,"Won") -> 176961 | C40: =COUNTIFS(Sales_Pipelines!$B$2:$B$8801,A40,Sales_Pipelines!$E$2:$E$8801,"Won") -> 105 | D40: =COUNTIF(Sales_Pipelines!$B$2:$B$8801,A40) -> 239 | E40: =IF(D40=0,0,C40/D40) -> 0.43933054 | F40: =IF(C40=0,0,B40/C40) -> 1685.3429 | G40: =VLOOKUP(A40,Sales_teams!$A$2:$C$36,2,FALSE) -> Melvin Marxen | H40: =VLOOKUP(A40,Sales_teams!$A$2:$C$36,3,FALSE) -> Central
A41: Darcel Schlecht | B41: =SUMIFS(Sales_Pipelines!$H$2:$H$8801,Sales_Pipelines!$B$2:$B$8801,A41,Sales_Pipelines!$E$2:$E$8801,"Won") -> 1153214 | C41: =COUNTIFS(Sales_Pipelines!$B$2:$B$8801,A41,Sales_Pipelines!$E$2:$E$8801,"Won") -> 349 | D41: =COUNTIF(Sales_Pipelines!$B$2:$B$8801,A41) -> 747 | E41: =IF(D41=0,0,C41/D41) -> 0.46720214 | F41: =IF(C41=0,0,B41/C41) -> 3304.3381 | G41: =VLOOKUP(A41,Sales_teams!$A$2:$C$36,2,FALSE) -> Melvin Marxen | H41: =VLOOKUP(A41,Sales_teams!$A$2:$C$36,3,FALSE) -> Central
A42: Mei-Mei Johns | B42: =SUMIFS(Sales_Pipelines!$H$2:$H$8801,Sales_Pipelines!$B$2:$B$8801,A42,Sales_Pipelines!$E$2:$E$8801,"Won") -> 0 | C42: =COUNTIFS(Sales_Pipelines!$B$2:$B$8801,A42,Sales_Pipelines!$E$2:$E$8801,"Won") -> 0 | D42: =COUNTIF(Sales_Pipelines!$B$2:$B$8801,A42) -> 0 | E42: =IF(D42=0,0,C42/D42) -> 0 | F42: =IF(C42=0,0,B42/C42) -> 0 | G42: =VLOOKUP(A42,Sales_teams!$A$2:$C$36,2,FALSE) -> Melvin Marxen | H42: =VLOOKUP(A42,Sales_teams!$A$2:$C$36,3,FALSE) -> Central
A43: Violet Mclelland | B43: =SUMIFS(Sales_Pipelines!$H$2:$H$8801,Sales_Pipelines!$B$2:$B$8801,A43,Sales_Pipelines!$E$2:$E$8801,"Won") -> 123431 | C43: =COUNTIFS(Sales_Pipelines!$B$2:$B$8801,A43,Sales_Pipelines!$E$2:$E$8801,"Won") -> 122 | D43: =COUNTIF(Sales_Pipelines!$B$2:$B$8801,A43) -> 261 | E43: =IF(D43=0,0,C43/D43) -> 0.46743295 | F43: =IF(C43=0,0,B43/C43) -> 1011.7295 | G43: =VLOOKUP(A43,Sales_teams!$A$2:$C$36,2,FALSE) -> Cara Losch | H43: =VLOOKUP(A43,Sales_teams!$A$2:$C$36,3,FALSE) -> East
... A66: Carl Lin | B66: =SUMIFS(Sales_Pipelines!$H$2:$H$8801,Sales_Pipelines!$B$2:$B$8801,A66,Sales_Pipelines!$E$2:$E$8801,"Won") -> 0 | C66: =COUNTIFS(Sales_Pipelines!$B$2:$B$8801,A66,Sales_Pipelines!$E$2:$E$8801,"Won") -> 0 | D66: =COUNTIF(Sales_Pipelines!$B$2:$B$8801,A66) -> 0 | E66: =IF(D66=0,0,C66/D66) -> 0 | F66: =IF(C66=0,0,B66/C66) -> 0 | G66: =VLOOKUP(A66,Sales_teams!$A$2:$C$36,2,FALSE) -> Summer Sewald | H66: =VLOOKUP(A66,Sales_teams!$A$2:$C$36,3,FALSE) -> West
A69: Regional Performance
A70: Regional Office | B70: Won Revenue | C70: Won Opportunities | D70: Total Opportunities | E70: Win Rate | F70: Avg. Won Deal Value
A71: Central | B71: =SUMIF($H$32:$H$66,A71,$B$32:$B$66) -> 3346293 | C71: =SUMIF($H$32:$H$66,A71,$C$32:$C$66) -> 1629 | D71: =SUMIF($H$32:$H$66,A71,$D$32:$D$66) -> 3512 | E71: =C71/D71 -> 0.46383827 | F71: =IF(C71=0,0,B71/C71) -> 2054.2007
A72: East | B72: =SUMIF($H$32:$H$66,A72,$B$32:$B$66) -> 3090594 | C72: =SUMIF($H$32:$H$66,A72,$C$32:$C$66) -> 1171 | D72: =SUMIF($H$32:$H$66,A72,$D$32:$D$66) -> 2291 | E72: =C72/D72 -> 0.51113051 | F72: =IF(C72=0,0,B72/C72) -> 2639.2775
A73: West | B73: =SUMIF($H$32:$H$66,A73,$B$32:$B$66) -> 3568647 | C73: =SUMIF($H$32:$H$66,A73,$C$32:$C$66) -> 1438 | D73: =SUMIF($H$32:$H$66,A73,$D$32:$D$66) -> 2997 | E73: =C73/D73 -> 0.47981315 | F73: =IF(C73=0,0,B73/C73) -> 2481.6739
A76: Manager Performance
A77: Manager | B77: Won Revenue | C77: Won Opportunities | D77: Total Opportunities | E77: Win Rate | F77: Avg. Won Deal Value
A78: Dustin Brinkmann | B78: =SUMIF($G$32:$G$66,A78,$B$32:$B$66) -> 1094363 | C78: =SUMIF($G$32:$G$66,A78,$C$32:$C$66) -> 747 | D78: =SUMIF($G$32:$G$66,A78,$D$32:$D$66) -> 1583 | E78: =IF(D78=0,0,C78/D78) -> 0.47188882 | F78: =IF(C78=0,0,B78/C78) -> 1465.0107
A79: Melvin Marxen | B79: =SUMIF($G$32:$G$66,A79,$B$32:$B$66) -> 2251930 | C79: =SUMIF($G$32:$G$66,A79,$C$32:$C$66) -> 882 | D79: =SUMIF($G$32:$G$66,A79,$D$32:$D$66) -> 1929 | E79: =IF(D79=0,0,C79/D79) -> 0.45723173 | F79: =IF(C79=0,0,B79/C79) -> 2553.2086
A80: Cara Losch | B80: =SUMIF($G$32:$G$66,A80,$B$32:$B$66) -> 1130049 | C80: =SUMIF($G$32:$G$66,A80,$C$32:$C$66) -> 480 | D80: =SUMIF($G$32:$G$66,A80,$D$32:$D$66) -> 964 | E80: =IF(D80=0,0,C80/D80) -> 0.49792531 | F80: =IF(C80=0,0,B80/C80) -> 2354.2688
A81: Rocco Neubert | B81: =SUMIF($G$32:$G$66,A81,$B$32:$B$66) -> 1960545 | C81: =SUMIF($G$32:$G$66,A81,$C$32:$C$66) -> 691 | D81: =SUMIF($G$32:$G$66,A81,$D$32:$D$66) -> 1327 | E81: =IF(D81=0,0,C81/D81) -> 0.52072344 | F81: =IF(C81=0,0,B81/C81) -> 2837.2576
A82: Celia Rouche | B82: =SUMIF($G$32:$G$66,A82,$B$32:$B$66) -> 1603897 | C82: =SUMIF($G$32:$G$66,A82,$C$32:$C$66) -> 610 | D82: =SUMIF($G$32:$G$66,A82,$D$32:$D$66) -> 1296 | E82: =IF(D82=0,0,C82/D82) -> 0.47067901 | F82: =IF(C82=0,0,B82/C82) -> 2629.3393
A83: Summer Sewald | B83: =SUMIF($G$32:$G$66,A83,$B$32:$B$66) -> 1964750 | C83: =SUMIF($G$32:$G$66,A83,$C$32:$C$66) -> 828 | D83: =SUMIF($G$32:$G$66,A83,$D$32:$D$66) -> 1701 | E83: =IF(D83=0,0,C83/D83) -> 0.48677249 | F83: =IF(C83=0,0,B83/C83) -> 2372.8865
A86: Quarterly Performance
A87: Quarter | B87: Won Revenue | C87: Won Opportunities | D87: Lost Opportunities | E87: Win Rate | F87: Avg. Won Deal Value
A88: Q1 2017 | B88: =SUMIFS(Sales_Pipelines!$H$2:$H$8801,Sales_Pipelines!$E$2:$E$8801,"Won",Sales_Pipelines!$G$2:$G$8801,">="&DATE(2017,1,1),Sales_Pipelines!$G$2:$G$8801,"<"&DATE(2017,4,1)) -> 1134672 | C88: =COUNTIFS(Sales_Pipelines!$E$2:$E$8801,"Won",Sales_Pipelines!$G$2:$G$8801,">="&DATE(2017,1,1),Sales_Pipelines!$G$2:$G$8801,"<"&DATE(2017,4,1)) -> 531 | D88: =COUNTIFS(Sales_Pipelines!$E$2:$E$8801,"Lost",Sales_Pipelines!$G$2:$G$8801,">="&DATE(2017,1,1),Sales_Pipelines!$G$2:$G$8801,"<"&DATE(2017,4,1)) -> 116 | E88: =IF(C88+D88=0,0,C88/(C88+D88)) -> 0.82071097 | F88: =IF(C88=0,0,B88/C88) -> 2136.8588
A89: Q2 2017 | B89: =SUMIFS(Sales_Pipelines!$H$2:$H$8801,Sales_Pipelines!$E$2:$E$8801,"Won",Sales_Pipelines!$G$2:$G$8801,">="&DATE(2017,4,1),Sales_Pipelines!$G$2:$G$8801,"<"&DATE(2017,7,1)) -> 3086111 | C89: =COUNTIFS(Sales_Pipelines!$E$2:$E$8801,"Won",Sales_Pipelines!$G$2:$G$8801,">="&DATE(2017,4,1),Sales_Pipelines!$G$2:$G$8801,"<"&DATE(2017,7,1)) -> 1254 | D89: =COUNTIFS(Sales_Pipelines!$E$2:$E$8801,"Lost",Sales_Pipelines!$G$2:$G$8801,">="&DATE(2017,4,1),Sales_Pipelines!$G$2:$G$8801,"<"&DATE(2017,7,1)) -> 778 | E89: =IF(C89+D89=0,0,C89/(C89+D89)) -> 0.61712598 | F89: =IF(C89=0,0,B89/C89) -> 2461.0136
A90: Q3 2017 | B90: =SUMIFS(Sales_Pipelines!$H$2:$H$8801,Sales_Pipelines!$E$2:$E$8801,"Won",Sales_Pipelines!$G$2:$G$8801,">="&DATE(2017,7,1),Sales_Pipelines!$G$2:$G$8801,"<"&DATE(2017,10,1)) -> 2982255 | C90: =COUNTIFS(Sales_Pipelines!$E$2:$E$8801,"Won",Sales_Pipelines!$G$2:$G$8801,">="&DATE(2017,7,1),Sales_Pipelines!$G$2:$G$8801,"<"&DATE(2017,10,1)) -> 1257 | D90: =COUNTIFS(Sales_Pipelines!$E$2:$E$8801,"Lost",Sales_Pipelines!$G$2:$G$8801,">="&DATE(2017,7,1),Sales_Pipelines!$G$2:$G$8801,"<"&DATE(2017,10,1)) -> 790 | E90: =IF(C90+D90=0,0,C90/(C90+D90)) -> 0.61406937 | F90: =IF(C90=0,0,B90/C90) -> 2372.5179
A91: Q4 2017 | B91: =SUMIFS(Sales_Pipelines!$H$2:$H$8801,Sales_Pipelines!$E$2:$E$8801,"Won",Sales_Pipelines!$G$2:$G$8801,">="&DATE(2017,10,1),Sales_Pipelines!$G$2:$G$8801,"<"&DATE(2018,1,1)) -> 2802496 | C91: =COUNTIFS(Sales_Pipelines!$E$2:$E$8801,"Won",Sales_Pipelines!$G$2:$G$8801,">="&DATE(2017,10,1),Sales_Pipelines!$G$2:$G$8801,"<"&DATE(2018,1,1)) -> 1196 | D91: =COUNTIFS(Sales_Pipelines!$E$2:$E$8801,"Lost",Sales_Pipelines!$G$2:$G$8801,">="&DATE(2017,10,1),Sales_Pipelines!$G$2:$G$8801,"<"&DATE(2018,1,1)) -> 789 | E91: =IF(C91+D91=0,0,C91/(C91+D91)) -> 0.60251889 | F91: =IF(C91=0,0,B91/C91) -> 2343.2241

Sheet Sales_Pipelines
A1: opportunity_id | B1: sales_agent | C1: product | D1: account | E1: deal_stage | F1: engage_date | G1: close_date | H1: close_value | I1: Unmatched_Product | J1: Expected_Value
A2: 1C1I7A6R | B2: Moses Frase | C2: GTX Plus Basic | D2: Cancity | E2: Won | F2: 42663 | G2: 42795 | H2: 1054 | I2: =IF(COUNTIF(Products!$A$2:$A$8,C2)=0,C2,"") | J2: =IF(OR(E2="Prospecting",E2="Engaging"),VLOOKUP(C2,Products!$A$2:$C$8,3,FALSE),0) -> 0
A3: Z063OYW0 | B3: Darcel Schlecht | C3: GTX Pro | D3: Isdom | E3: Won | F3: 42668 | G3: 42805 | H3: 4514 | I3: =IF(COUNTIF(Products!$A$2:$A$8,C3)=0,C3,"") | J3: =IF(OR(E3="Prospecting",E3="Engaging"),VLOOKUP(C3,Products!$A$2:$C$8,3,FALSE),0) -> 0
A4: EC4QE1BX | B4: Darcel Schlecht | C4: MG Special | D4: Cancity | E4: Won | F4: 42668 | G4: 42801 | H4: 50 | I4: =IF(COUNTIF(Products!$A$2:$A$8,C4)=0,C4,"") | J4: =IF(OR(E4="Prospecting",E4="Engaging"),VLOOKUP(C4,Products!$A$2:$C$8,3,FALSE),0) -> 0
A5: MV1LWRNH | B5: Moses Frase | C5: GTX Basic | D5: Codehow | E5: Won | F5: 42668 | G5: 42803 | H5: 588 | I5: =IF(COUNTIF(Products!$A$2:$A$8,C5)=0,C5,"") | J5: =IF(OR(E5="Prospecting",E5="Engaging"),VLOOKUP(C5,Products!$A$2:$C$8,3,FALSE),0) -> 0 | L5: =MIN(Sales_Pipelines!G2:G8801) -> 42795
A6: PE84CX4O | B6: Zane Levy | C6: GTX Basic | D6: Hatfan | E6: Won | F6: 42668 | G6: 42796 | H6: 517 | I6: =IF(COUNTIF(Products!$A$2:$A$8,C6)=0,C6,"") | J6: =IF(OR(E6="Prospecting",E6="Engaging"),VLOOKUP(C6,Products!$A$2:$C$8,3,FALSE),0) -> 0 | L6: =MAX(Sales_Pipelines!G2:G8801) -> 43100
A7: ZNBS69V1 | B7: Anna Snelling | C7: MG Special | D7: Ron-tech | E7: Won | F7: 42672 | G7: 42795 | H7: 49 | I7: =IF(COUNTIF(Products!$A$2:$A$8,C7)=0,C7,"") | J7: =IF(OR(E7="Prospecting",E7="Engaging"),VLOOKUP(C7,Products!$A$2:$C$8,3,FALSE),0) -> 0
A8: 9ME3374G | B8: Vicki Laflamme | C8: MG Special | D8: J-Texon | E8: Won | F8: 42673 | G8: 42796 | H8: 57 | I8: =IF(COUNTIF(Products!$A$2:$A$8,C8)=0,C8,"") | J8: =IF(OR(E8="Prospecting",E8="Engaging"),VLOOKUP(C8,Products!$A$2:$C$8,3,FALSE),0) -> 0
A9: 7GN8Q4LL | B9: Markita Hansen | C9: GTX Basic | D9: Cheers | E9: Won | F9: 42675 | G9: 42801 | H9: 601 | I9: =IF(COUNTIF(Products!$A$2:$A$8,C9)=0,C9,"") | J9: =IF(OR(E9="Prospecting",E9="Engaging"),VLOOKUP(C9,Products!$A$2:$C$8,3,FALSE),0) -> 0
A10: OLK9LKZB | B10: Niesha Huffines | C10: GTX Plus Basic | D10: Zumgoity | E10: Won | F10: 42675 | G10: 42797 | H10: 1026 | I10: =IF(COUNTIF(Products!$A$2:$A$8,C10)=0,C10,"") | J10: =IF(OR(E10="Prospecting",E10="Engaging"),VLOOKUP(C10,Products!$A$2:$C$8,3,FALSE),0) -> 0
A11: HAXMC4IX | B11: James Ascencio | C11: MG Advanced | E11: Engaging | F11: 42677 | I11: =IF(COUNTIF(Products!$A$2:$A$8,C11)=0,C11,"") | J11: =IF(OR(E11="Prospecting",E11="Engaging"),VLOOKUP(C11,Products!$A$2:$C$8,3,FALSE),0) -> 3393
A12: NL3JZH1Z | B12: Anna Snelling | C12: MG Special | D12: Bioholding | E12: Won | F12: 42678 | G12: 42804 | H12: 53 | I12: =IF(COUNTIF(Products!$A$2:$A$8,C12)=0,C12,"") | J12: =IF(OR(E12="Prospecting",E12="Engaging"),VLOOKUP(C12,Products!$A$2:$C$8,3,FALSE),0) -> 0
A13: KWVA7VR1 | B13: Gladys Colclough | C13: GTX Pro | D13: Genco Pura Olive Oil Company | E13: Lost | F13: 42678 | G13: 42812 | H13: 0 | I13: =IF(COUNTIF(Products!$A$2:$A$8,C13)=0,C13,"") | J13: =IF(OR(E13="Prospecting",E13="Engaging"),VLOOKUP(C13,Products!$A$2:$C$8,3,FALSE),0) -> 0
A14: S8DX3XOU | B14: James Ascencio | C14: GTX Plus Pro | D14: Sunnamplex | E14: Won | F14: 42678 | G14: 42804 | H14: 5169 | I14: =IF(COUNTIF(Products!$A$2:$A$8,C14)=0,C14,"") | J14: =IF(OR(E14="Prospecting",E14="Engaging"),VLOOKUP(C14,Products!$A$2:$C$8,3,FALSE),0) -> 0
A15: ENB2XD8G | B15: Maureen Marcano | C15: GTX Plus Pro | D15: Sonron | E15: Won | F15: 42678 | G15: 42800 | H15: 4631 | I15: =IF(COUNTIF(Products!$A$2:$A$8,C15)=0,C15,"") | J15: =IF(OR(E15="Prospecting",E15="Engaging"),VLOOKUP(C15,Products!$A$2:$C$8,3,FALSE),0) -> 0
A16: 09YE9QOV | B16: Hayden Neloms | C16: MG Advanced | D16: Finjob | E16: Won | F16: 42679 | G16: 42805 | H16: 3393 | I16: =IF(COUNTIF(Products!$A$2:$A$8,C16)=0,C16,"") | J16: =IF(OR(E16="Prospecting",E16="Engaging"),VLOOKUP(C16,Products!$A$2:$C$8,3,FALSE),0) -> 0
A17: 3F5MZNEH | B17: Rosalina Dieter | C17: MG Special | D17: Sonron | E17: Lost | F17: 42679 | G17: 42797 | H17: 0 | I17: =IF(COUNTIF(Products!$A$2:$A$8,C17)=0,C17,"") | J17: =IF(OR(E17="Prospecting",E17="Engaging"),VLOOKUP(C17,Products!$A$2:$C$8,3,FALSE),0) -> 0
A18: M6WEJXC0 | B18: Rosalina Dieter | C18: MG Advanced | D18: Scotfind | E18: Won | F18: 42679 | G18: 42800 | H18: 3284 | I18: =IF(COUNTIF(Products!$A$2:$A$8,C18)=0,C18,"") | J18: =IF(OR(E18="Prospecting",E18="Engaging"),VLOOKUP(C18,Products!$A$2:$C$8,3,FALSE),0) -> 0
A19: 6PTR7VBR | B19: Versie Hillebrand | C19: MG Special | D19: Treequote | E19: Won | F19: 42680 | G19: 42799 | H19: 61 | I19: =IF(COUNTIF(Products!$A$2:$A$8,C19)=0,C19,"") | J19: =IF(OR(E19="Prospecting",E19="Engaging"),VLOOKUP(C19,Products!$A$2:$C$8,3,FALSE),0) -> 0
A20: 902REDPA | B20: Daniell Hammack | C20: GTX Pro | D20: Xx-zobam | E20: Lost | F20: 42681 | G20: 42803 | H20: 0 | I20: =IF(COUNTIF(Products!$A$2:$A$8,C20)=0,C20,"") | J20: =IF(OR(E20="Prospecting",E20="Engaging"),VLOOKUP(C20,Products!$A$2:$C$8,3,FALSE),0) -> 0
A21: 5J9CMGDV | B21: Elease Gluck | C21: MG Special | D21: Rantouch | E21: Won | F21: 42681 | G21: 42802 | H21: 46 | I21: =IF(COUNTIF(Products!$A$2:$A$8,C21)=0,C21,"") | J21: =IF(OR(E21="Prospecting",E21="Engaging"),VLOOKUP(C21,Products!$A$2:$C$8,3,FALSE),0) -> 0
A22: JJXRR8R6 | B22: James Ascencio | C22: GTX Plus Pro | D22: Fasehatice | E22: Lost | F22: 42681 | G22: 42811 | H22: 0 | I22: =IF(COUNTIF(Products!$A$2:$A$8,C22)=0,C22,"") | J22: =IF(OR(E22="Prospecting",E22="Engaging"),VLOOKUP(C22,Products!$A$2:$C$8,3,FALSE),0) -> 0
A23: WF4HA5NW | B23: Moses Frase | C23: MG Special | D23: Ron-tech | E23: Won | F23: 42681 | G23: 42812 | H23: 50 | I23: =IF(COUNTIF(Products!$A$2:$A$8,C23)=0,C23,"") | J23: =IF(OR(E23="Prospecting",E23="Engaging"),VLOOKUP(C23,Products!$A$2:$C$8,3,FALSE),0) -> 0
... A26: SBCR987L | B26: Kami Bicknell | C26: GTX Basic | D26: Zoomit | E26: Won | F26: 42684 | G26: 42817 | H26: 590 | I26: =IF(COUNTIF(Products!$A$2:$A$8,C26)=0,C26,"") | J26: =IF(OR(E26="Prospecting",E26="Engaging"),VLOOKUP(C26,Products!$A$2:$C$8,3,FALSE),0) -> 0
A27: UP409DSB | B27: Maureen Marcano | C27: MG Advanced | D27: Ganjaflex | E27: Engaging | F27: 42684 | I27: =IF(COUNTIF(Products!$A$2:$A$8,C27)=0,C27,"") | J27: =IF(OR(E27="Prospecting",E27="Engaging"),VLOOKUP(C27,Products!$A$2:$C$8,3,FALSE),0) -> 3393
A28: JSD4APT2 | B28: Versie Hillebrand | C28: MG Special | D28: Bioholding | E28: Won | F28: 42684 | G28: 42806 | H28: 61 | I28: =IF(COUNTIF(Products!$A$2:$A$8,C28)=0,C28,"") | J28: =IF(OR(E28="Prospecting",E28="Engaging"),VLOOKUP(C28,Products!$A$2:$C$8,3,FALSE),0) -> 0
A29: AO9Z2D17 | B29: Violet Mclelland | C29: GTX Plus Pro | D29: Xx-zobam | E29: Lost | F29: 42684 | G29: 42805 | H29: 0 | I29: =IF(COUNTIF(Products!$A$2:$A$8,C29)=0,C29,"") | J29: =IF(OR(E29="Prospecting",E29="Engaging"),VLOOKUP(C29,Products!$A$2:$C$8,3,FALSE),0) -> 0
A30: 5M58DTJK | B30: Elease Gluck | C30: MG Special | D30: Cheers | E30: Won | F30: 42685 | G30: 42799 | H30: 58 | I30: =IF(COUNTIF(Products!$A$2:$A$8,C30)=0,C30,"") | J30: =IF(OR(E30="Prospecting",E30="Engaging"),VLOOKUP(C30,Products!$A$2:$C$8,3,FALSE),0) -> 0
A31: KNY1OSAB | B31: Maureen Marcano | C31: GTX Pro | D31: Labdrill | E31: Won | F31: 42685 | G31: 42808 | H31: 4899 | I31: =IF(COUNTIF(Products!$A$2:$A$8,C31)=0,C31,"") | J31: =IF(OR(E31="Prospecting",E31="Engaging"),VLOOKUP(C31,Products!$A$2:$C$8,3,FALSE),0) -> 0
A32: EAZDUUM9 | B32: Rosie Papadopoulos | C32: MG Advanced | D32: Zotware | E32: Lost | F32: 42685 | G32: 42795 | H32: 0 | I32: =IF(COUNTIF(Products!$A$2:$A$8,C32)=0,C32,"") | J32: =IF(OR(E32="Prospecting",E32="Engaging"),VLOOKUP(C32,Products!$A$2:$C$8,3,FALSE),0) -> 0
A33: 2STUSOFE | B33: Versie Hillebrand | C33: MG Special | D33: dambase | E33: Won | F33: 42685 | G33: 42797 | H33: 67 | I33: =IF(COUNTIF(Products!$A$2:$A$8,C33)=0,C33,"") | J33: =IF(OR(E33="Prospecting",E33="Engaging"),VLOOKUP(C33,Products!$A$2:$C$8,3,FALSE),0) -> 0
A34: JYKM0B00 | B34: James Ascencio | C34: GTX Pro | D34: Xx-holding | E34: Won | F34: 42686 | G34: 42800 | H34: 4338 | I34: =IF(COUNTIF(Products!$A$2:$A$8,C34)=0,C34,"") | J34: =IF(OR(E34="Prospecting",E34="Engaging"),VLOOKUP(C34,Products!$A$2:$C$8,3,FALSE),0) -> 0
A35: KU28360J | B35: Kary Hendrixson | C35: GTX Basic | D35: Fasehatice | E35: Won | F35: 42686 | G35: 42813 | H35: 578 | I35: =IF(COUNTIF(Products!$A$2:$A$8,C35)=0,C35,"") | J35: =IF(OR(E35="Prospecting",E35="Engaging"),VLOOKUP(C35,Products!$A$2:$C$8,3,FALSE),0) -> 0
A36: N4SD17JR | B36: Reed Clapper | C36: GTX Basic | D36: Acme Corporation | E36: Won | F36: 42686 | G36: 42795 | H36: 556 | I36: =IF(COUNTIF(Products!$A$2:$A$8,C36)=0,C36,"") | J36: =IF(OR(E36="Prospecting",E36="Engaging"),VLOOKUP(C36,Products!$A$2:$C$8,3,FALSE),0) -> 0
A37: E67P9Y3Q | B37: Rosalina Dieter | C37: GTX Basic | D37: Green-Plus | E37: Won | F37: 42686 | G37: 42797 | H37: 635 | I37: =IF(COUNTIF(Products!$A$2:$A$8,C37)=0,C37,"") | J37: =IF(OR(E37="Prospecting",E37="Engaging"),VLOOKUP(C37,Products!$A$2:$C$8,3,FALSE),0) -> 0
A38: AT3MMVIS | B38: Wilburn Farren | C38: MG Advanced | D38: The New York Inquirer | E38: Won | F38: 42686 | G38: 42801 | H38: 3045 | I38: =IF(COUNTIF(Products!$A$2:$A$8,C38)=0,C38,"") | J38: =IF(OR(E38="Prospecting",E38="Engaging"),VLOOKUP(C38,Products!$A$2:$C$8,3,FALSE),0) -> 0
A39: REJ11LRY | B39: Garret Kinder | C39: GTX Plus Basic | D39: Mathtouch | E39: Won | F39: 42687 | G39: 42808 | H39: 1233 | I39: =IF(COUNTIF(Products!$A$2:$A$8,C39)=0,C39,"") | J39: =IF(OR(E39="Prospecting",E39="Engaging"),VLOOKUP(C39,Products!$A$2:$C$8,3,FALSE),0) -> 0
... A43: CZVN09WN | B43: Darcel Schlecht | C43: GTX Plus Basic | D43: Konmatfix | E43: Won | F43: 42688 | G43: 42814 | H43: 1170 | I43: =IF(COUNTIF(Products!$A$2:$A$8,C43)=0,C43,"") | J43: =IF(OR(E43="Prospecting",E43="Engaging"),VLOOKUP(C43,Products!$A$2:$C$8,3,FALSE),0) -> 0
A44: EG7OFLFR | B44: Kami Bicknell | C44: GTX Basic | E44: Engaging | F44: 42688 | I44: =IF(COUNTIF(Products!$A$2:$A$8,C44)=0,C44,"") | J44: =IF(OR(E44="Prospecting",E44="Engaging"),VLOOKUP(C44,Products!$A$2:$C$8,3,FALSE),0) -> 550
A45: 30UQWUKB | B45: Marty Freudenburg | C45: GTX Plus Basic | D45: Genco Pura Olive Oil Company | E45: Won | F45: 42689 | G45: 42814 | H45: 1162 | I45: =IF(COUNTIF(Products!$A$2:$A$8,C45)=0,C45,"") | J45: =IF(OR(E45="Prospecting",E45="Engaging"),VLOOKUP(C45,Products!$A$2:$C$8,3,FALSE),0) -> 0
A46: OLVI7L8M | B46: Cassey Cress | C46: GTX Pro | E46: Engaging | F46: 42690 | I46: =IF(COUNTIF(Products!$A$2:$A$8,C46)=0,C46,"") | J46: =IF(OR(E46="Prospecting",E46="Engaging"),VLOOKUP(C46,Products!$A$2:$C$8,3,FALSE),0) -> 4821
A47: 97UN20YY | B47: Darcel Schlecht | C47: MG Advanced | D47: Conecom | E47: Won | F47: 42690 | G47: 42808 | H47: 3725 | I47: =IF(COUNTIF(Products!$A$2:$A$8,C47)=0,C47,"") | J47: =IF(OR(E47="Prospecting",E47="Engaging"),VLOOKUP(C47,Products!$A$2:$C$8,3,FALSE),0) -> 0
A48: JXLERZ9O | B48: Kary Hendrixson | C48: GTX Basic | D48: Golddex | E48: Won | F48: 42690 | G48: 42825 | H48: 559 | I48: =IF(COUNTIF(Products!$A$2:$A$8,C48)=0,C48,"") | J48: =IF(OR(E48="Prospecting",E48="Engaging"),VLOOKUP(C48,Products!$A$2:$C$8,3,FALSE),0) -> 0
A49: 6ROE69W5 | B49: Rosalina Dieter | C49: GTX Basic | D49: Plexzap | E49: Lost | F49: 42690 | G49: 42805 | H49: 0 | I49: =IF(COUNTIF(Products!$A$2:$A$8,C49)=0,C49,"") | J49: =IF(OR(E49="Prospecting",E49="Engaging"),VLOOKUP(C49,Products!$A$2:$C$8,3,FALSE),0) -> 0
A50: 0DFXFKT7 | B50: Darcel Schlecht | C50: GTX Plus Basic | D50: Rundofase | E50: Lost | F50: 42691 | G50: 42815 | H50: 0 | I50: =IF(COUNTIF(Products!$A$2:$A$8,C50)=0,C50,"") | J50: =IF(OR(E50="Prospecting",E50="Engaging"),VLOOKUP(C50,Products!$A$2:$C$8,3,FALSE),0) -> 0
A51: XKMZVSN4 | B51: James Ascencio | C51: GTX Plus Pro | D51: Sonron | E51: Won | F51: 42691 | G51: 42799 | H51: 4667 | I51: =IF(COUNTIF(Products!$A$2:$A$8,C51)=0,C51,"") | J51: =IF(OR(E51="Prospecting",E51="Engaging"),VLOOKUP(C51,Products!$A$2:$C$8,3,FALSE),0) -> 0
A52: IU8V0BZK | B52: Marty Freudenburg | C52: GTX Plus Basic | D52: Finhigh | E52: Won | F52: 42691 | G52: 42811 | H52: 903 | I52: =IF(COUNTIF(Products!$A$2:$A$8,C52)=0,C52,"") | J52: =IF(OR(E52="Prospecting",E52="Engaging"),VLOOKUP(C52,Products!$A$2:$C$8,3,FALSE),0) -> 0
A53: XY42936P | B53: Maureen Marcano | C53: GTX Plus Basic | D53: Finjob | E53: Won | F53: 42691 | G53: 42807 | H53: 1180 | I53: =IF(COUNTIF(Products!$A$2:$A$8,C53)=0,C53,"") | J53: =IF(OR(E53="Prospecting",E53="Engaging"),VLOOKUP(C53,Products!$A$2:$C$8,3,FALSE),0) -> 0
A54: XRN54MBM | B54: Niesha Huffines | C54: GTX Basic | D54: Ron-tech | E54: Won | F54: 42691 | G54: 42799 | H54: 487 | I54: =IF(COUNTIF(Products!$A$2:$A$8,C54)=0,C54,"") | J54: =IF(OR(E54="Prospecting",E54="Engaging"),VLOOKUP(C54,Products!$A$2:$C$8,3,FALSE),0) -> 0
A55: 2V848WZD | B55: Lajuana Vencill | C55: MG Advanced | D55: Stanredtax | E55: Won | F55: 42692 | G55: 42798 | H55: 3180 | I55: =IF(COUNTIF(Products!$A$2:$A$8,C55)=0,C55,"") | J55: =IF(OR(E55="Prospecting",E55="Engaging"),VLOOKUP(C55,Products!$A$2:$C$8,3,FALSE),0) -> 0
A56: ONYNTUCG | B56: Darcel Schlecht | C56: GTX Pro | D56: Funholding | E56: Lost | F56: 42693 | G56: 42811 | H56: 0 | I56: =IF(COUNTIF(Products!$A$2:$A$8,C56)=0,C56,"") | J56: =IF(OR(E56="Prospecting",E56="Engaging"),VLOOKUP(C56,Products!$A$2:$C$8,3,FALSE),0) -> 0
A57: HIOHX80Y | B57: Darcel Schlecht | C57: MG Advanced | D57: Gogozoom | E57: Won | F57: 42693 | G57: 42812 | H57: 3563 | I57: =IF(COUNTIF(Products!$A$2:$A$8,C57)=0,C57,"") | J57: =IF(OR(E57="Prospecting",E57="Engaging"),VLOOKUP(C57,Products!$A$2:$C$8,3,FALSE),0) -> 0
A58: F5U1ACDD | B58: Kami Bicknell | C58: GTX Plus Basic | E58: Engaging | F58: 42693 | I58: =IF(COUNTIF(Products!$A$2:$A$8,C58)=0,C58,"") | J58: =IF(OR(E58="Prospecting",E58="Engaging"),VLOOKUP(C58,Products!$A$2:$C$8,3,FALSE),0) -> 1096
A59: LPKT07PV | B59: Boris Faz | C59: GTX Pro | D59: Opentech | E59: Won | F59: 42694 | G59: 42817 | H59: 4704 | I59: =IF(COUNTIF(Products!$A$2:$A$8,C59)=0,C59,"") | J59: =IF(OR(E59="Prospecting",E59="Engaging"),VLOOKUP(C59,Products!$A$2:$C$8,3,FALSE),0) -> 0
A60: WPB2SLIG | B60: Donn Cantrell | C60: GTX Plus Pro | D60: Silis | E60: Won | F60: 42694 | G60: 42808 | H60: 5585 | I60: =IF(COUNTIF(Products!$A$2:$A$8,C60)=0,C60,"") | J60: =IF(OR(E60="Prospecting",E60="Engaging"),VLOOKUP(C60,Products!$A$2:$C$8,3,FALSE),0) -> 0
A61: XUSUEAV7 | B61: Elease Gluck | C61: GTK 500 | D61: Zoomit | E61: Won | F61: 42694 | G61: 42803 | H61: 25897 | I61: =IF(COUNTIF(Products!$A$2:$A$8,C61)=0,C61,"") | J61: =IF(OR(E61="Prospecting",E61="Engaging"),VLOOKUP(C61,Products!$A$2:$C$8,3,FALSE),0) -> 0
A62: ZZY4516R | B62: Hayden Neloms | C62: MG Advanced | E62: Engaging | F62: 42694 | I62: =IF(COUNTIF(Products!$A$2:$A$8,C62)=0,C62,"") | J62: =IF(OR(E62="Prospecting",E62="Engaging"),VLOOKUP(C62,Products!$A$2:$C$8,3,FALSE),0) -> 3393
A63: 3TYPII47 | B63: Kami Bicknell | C63: GTX Plus Basic | D63: Goodsilron | E63: Won | F63: 42694 | G63: 42797 | H63: 1207 | I63: =IF(COUNTIF(Products!$A$2:$A$8,C63)=0,C63,"") | J63: =IF(OR(E63="Prospecting",E63="Engaging"),VLOOKUP(C63,Products!$A$2:$C$8,3,FALSE),0) -> 0
A64: 7WAX8Z8O | B64: Lajuana Vencill | C64: MG Advanced | D64: Cancity | E64: Lost | F64: 42694 | G64: 42802 | H64: 0 | I64: =IF(COUNTIF(Products!$A$2:$A$8,C64)=0,C64,"") | J64: =IF(OR(E64="Prospecting",E64="Engaging"),VLOOKUP(C64,Products!$A$2:$C$8,3,FALSE),0) -> 0
A65: MYDUMR3R | B65: Lajuana Vencill | C65: GTX Basic | D65: Rangreen | E65: Won | F65: 42694 | G65: 42798 | H65: 559 | I65: =IF(COUNTIF(Products!$A$2:$A$8,C65)=0,C65,"") | J65: =IF(OR(E65="Prospecting",E65="Engaging"),VLOOKUP(C65,Products!$A$2:$C$8,3,FALSE),0) -> 0
A66: 0DRC1U9Q | B66: Maureen Marcano | C66: GTX Basic | D66: Green-Plus | E66: Engaging | F66: 42694 | I66: =IF(COUNTIF(Products!$A$2:$A$8,C66)=0,C66,"") | J66: =IF(OR(E66="Prospecting",E66="Engaging"),VLOOKUP(C66,Products!$A$2:$C$8,3,FALSE),0) -> 550
A67: 37JFKD4I | B67: Niesha Huffines | C67: GTX Plus Basic | D67: dambase | E67: Won | F67: 42694 | G67: 42803 | H67: 1033 | I67: =IF(COUNTIF(Products!$A$2:$A$8,C67)=0,C67,"") | J67: =IF(OR(E67="Prospecting",E67="Engaging"),VLOOKUP(C67,Products!$A$2:$C$8,3,FALSE),0) -> 0
A68: 25YKPHX8 | B68: Donn Cantrell | C68: GTX Basic | D68: Kan-code | E68: Won | F68: 42695 | G68: 42815 | H68: 462 | I68: =IF(COUNTIF(Products!$A$2:$A$8,C68)=0,C68,"") | J68: =IF(OR(E68="Prospecting",E68="Engaging"),VLOOKUP(C68,Products!$A$2:$C$8,3,FALSE),0) -> 0
A69: BXXMA7F3 | B69: Hayden Neloms | C69: MG Advanced | D69: Nam-zim | E69: Lost | F69: 42695 | G69: 42795 | H69: 0 | I69: =IF(COUNTIF(Products!$A$2:$A$8,C69)=0,C69,"") | J69: =IF(OR(E69="Prospecting",E69="Engaging"),VLOOKUP(C69,Products!$A$2:$C$8,3,FALSE),0) -> 0
A70: GIUUTBXM | B70: Kary Hendrixson | C70: GTX Pro | D70: Y-corporation | E70: Won | F70: 42695 | G70: 42808 | H70: 5539 | I70: =IF(COUNTIF(Products!$A$2:$A$8,C70)=0,C70,"") | J70: =IF(OR(E70="Prospecting",E70="Engaging"),VLOOKUP(C70,Products!$A$2:$C$8,3,FALSE),0) -> 0
A71: MFX2LR1Q | B71: Lajuana Vencill | C71: MG Advanced | D71: Ron-tech | E71: Won | F71: 42695 | G71: 42809 | H71: 3573 | I71: =IF(COUNTIF(Products!$A$2:$A$8,C71)=0,C71,"") | J71: =IF(OR(E71="Prospecting",E71="Engaging"),VLOOKUP(C71,Products!$A$2:$C$8,3,FALSE),0) -> 0
A72: DUHE9FLY | B72: Marty Freudenburg | C72: GTX Pro | D72: Conecom | E72: Won | F72: 42695 | G72: 42795 | H72: 4926 | I72: =IF(COUNTIF(Products!$A$2:$A$8,C72)=0,C72,"") | J72: =IF(OR(E72="Prospecting",E72="Engaging"),VLOOKUP(C72,Products!$A$2:$C$8,3,FALSE),0) -> 0
A73: 96BSG7R1 | B73: Zane Levy | C73: GTX Plus Basic | D73: Sunnamplex | E73: Lost | F73: 42695 | G73: 42811 | H73: 0 | I73: =IF(COUNTIF(Products!$A$2:$A$8,C73)=0,C73,"") | J73: =IF(OR(E73="Prospecting",E73="Engaging"),VLOOKUP(C73,Products!$A$2:$C$8,3,FALSE),0) -> 0
A74: 7FQMSWIX | B74: Corliss Cosme | C74: MG Special | D74: Bioplex | E74: Won | F74: 42696 | G74: 42798 | H74: 62 | I74: =IF(COUNTIF(Products!$A$2:$A$8,C74)=0,C74,"") | J74: =IF(OR(E74="Prospecting",E74="Engaging"),VLOOKUP(C74,Products!$A$2:$C$8,3,FALSE),0) -> 0
A75: C20AVXN7 | B75: Darcel Schlecht | C75: GTX Pro | D75: Gogozoom | E75: Won | F75: 42696 | G75: 42808 | H75: 4359 | I75: =IF(COUNTIF(Products!$A$2:$A$8,C75)=0,C75,"") | J75: =IF(OR(E75="Prospecting",E75="Engaging"),VLOOKUP(C75,Products!$A$2:$C$8,3,FALSE),0) -> 0
A76: GS1QVWCR | B76: Kami Bicknell | C76: GTX Basic | D76: Plusstrip | E76: Won | F76: 42696 | G76: 42825 | H76: 566 | I76: =IF(COUNTIF(Products!$A$2:$A$8,C76)=0,C76,"") | J76: =IF(OR(E76="Prospecting",E76="Engaging"),VLOOKUP(C76,Products!$A$2:$C$8,3,FALSE),0) -> 0
A77: ZWH8FXY3 | B77: Marty Freudenburg | C77: GTX Basic | D77: Toughzap | E77: Won | F77: 42696 | G77: 42797 | H77: 508 | I77: =IF(COUNTIF(Products!$A$2:$A$8,C77)=0,C77,"") | J77: =IF(OR(E77="Prospecting",E77="Engaging"),VLOOKUP(C77,Products!$A$2:$C$8,3,FALSE),0) -> 0
A78: 2U94Y3Q9 | B78: Rosie Papadopoulos | C78: MG Advanced | D78: Vehement Capital Partners | E78: Lost | F78: 42696 | G78: 42814 | H78: 0 | I78: =IF(COUNTIF(Products!$A$2:$A$8,C78)=0,C78,"") | J78: =IF(OR(E78="Prospecting",E78="Engaging"),VLOOKUP(C78,Products!$A$2:$C$8,3,FALSE),0) -> 0
... A80: B6B0PNR2 | B80: Vicki Laflamme | C80: GTX Pro | D80: Dalttechnology | E80: Won | F80: 42696 | G80: 42799 | H80: 4899 | I80: =IF(COUNTIF(Products!$A$2:$A$8,C80)=0,C80,"") | J80: =IF(OR(E80="Prospecting",E80="Engaging"),VLOOKUP(C80,Products!$A$2:$C$8,3,FALSE),0) -> 0
A81: M7I5O9YU | B81: Corliss Cosme | C81: GTX Basic | D81: Cheers | E81: Engaging | F81: 42697 | I81: =IF(COUNTIF(Products!$A$2:$A$8,C81)=0,C81,"") | J81: =IF(OR(E81="Prospecting",E81="Engaging"),VLOOKUP(C81,Products!$A$2:$C$8,3,FALSE),0) -> 550
A82: LXZA2OSZ | B82: Corliss Cosme | C82: GTX Plus Pro | D82: Ontomedia | E82: Won | F82: 42697 | G82: 42797 | H82: 5790 | I82: =IF(COUNTIF(Products!$A$2:$A$8,C82)=0,C82,"") | J82: =IF(OR(E82="Prospecting",E82="Engaging"),VLOOKUP(C82,Products!$A$2:$C$8,3,FALSE),0) -> 0
A83: N0ONCYVZ | B83: Donn Cantrell | C83: MG Special | D83: Kinnamplus | E83: Lost | F83: 42697 | G83: 42824 | H83: 0 | I83: =IF(COUNTIF(Products!$A$2:$A$8,C83)=0,C83,"") | J83: =IF(OR(E83="Prospecting",E83="Engaging"),VLOOKUP(C83,Products!$A$2:$C$8,3,FALSE),0) -> 0
A84: GYB4W2AU | B84: Elease Gluck | C84: MG Advanced | E84: Engaging | F84: 42697 | I84: =IF(COUNTIF(Products!$A$2:$A$8,C84)=0,C84,"") | J84: =IF(OR(E84="Prospecting",E84="Engaging"),VLOOKUP(C84,Products!$A$2:$C$8,3,FALSE),0) -> 3393
A85: 513DPFX5 | B85: Gladys Colclough | C85: GTX Pro | D85: Codehow | E85: Won | F85: 42697 | G85: 42797 | H85: 4438 | I85: =IF(COUNTIF(Products!$A$2:$A$8,C85)=0,C85,"") | J85: =IF(OR(E85="Prospecting",E85="Engaging"),VLOOKUP(C85,Products!$A$2:$C$8,3,FALSE),0) -> 0
A86: RU023K5W | B86: Gladys Colclough | C86: MG Advanced | D86: Finhigh | E86: Won | F86: 42697 | G86: 42811 | H86: 2972 | I86: =IF(COUNTIF(Products!$A$2:$A$8,C86)=0,C86,"") | J86: =IF(OR(E86="Prospecting",E86="Engaging"),VLOOKUP(C86,Products!$A$2:$C$8,3,FALSE),0) -> 0
A87: VDIU10RV | B87: Markita Hansen | C87: MG Special | D87: Lexiqvolax | E87: Engaging | F87: 42697 | I87: =IF(COUNTIF(Products!$A$2:$A$8,C87)=0,C87,"") | J87: =IF(OR(E87="Prospecting",E87="Engaging"),VLOOKUP(C87,Products!$A$2:$C$8,3,FALSE),0) -> 55
A88: BZCBQ514 | B88: Markita Hansen | C88: GTX Basic | D88: Y-corporation | E88: Won | F88: 42697 | G88: 42795 | H88: 523 | I88: =IF(COUNTIF(Products!$A$2:$A$8,C88)=0,C88,"") | J88: =IF(OR(E88="Prospecting",E88="Engaging"),VLOOKUP(C88,Products!$A$2:$C$8,3,FALSE),0) -> 0
A89: HEE6P0QH | B89: Anna Snelling | C89: MG Advanced | D89: Statholdings | E89: Won | F89: 42698 | G89: 42819 | H89: 3647 | I89: =IF(COUNTIF(Products!$A$2:$A$8,C89)=0,C89,"") | J89: =IF(OR(E89="Prospecting",E89="Engaging"),VLOOKUP(C89,Products!$A$2:$C$8,3,FALSE),0) -> 0
A90: L8CHRJ2B | B90: Cassey Cress | C90: MG Advanced | D90: Umbrella Corporation | E90: Won | F90: 42698 | G90: 42795 | H90: 4200 | I90: =IF(COUNTIF(Products!$A$2:$A$8,C90)=0,C90,"") | J90: =IF(OR(E90="Prospecting",E90="Engaging"),VLOOKUP(C90,Products!$A$2:$C$8,3,FALSE),0) -> 0
A91: 579LZ3F9 | B91: Daniell Hammack | C91: GTX Plus Basic | D91: J-Texon | E91: Engaging | F91: 42698 | I91: =IF(COUNTIF(Products!$A$2:$A$8,C91)=0,C91,"") | J91: =IF(OR(E91="Prospecting",E91="Engaging"),VLOOKUP(C91,Products!$A$2:$C$8,3,FALSE),0) -> 1096
A92: SU8JNMP4 | B92: Kami Bicknell | C92: GTX Plus Basic | D92: Bubba Gump | E92: Engaging | F92: 42698 | I92: =IF(COUNTIF(Products!$A$2:$A$8,C92)=0,C92,"") | J92: =IF(OR(E92="Prospecting",E92="Engaging"),VLOOKUP(C92,Products!$A$2:$C$8,3,FALSE),0) -> 1096
A93: V2X2KMUR | B93: Kami Bicknell | C93: GTX Plus Basic | D93: Faxquote | E93: Won | F93: 42698 | G93: 42822 | H93: 1059 | I93: =IF(COUNTIF(Products!$A$2:$A$8,C93)=0,C93,"") | J93: =IF(OR(E93="Prospecting",E93="Engaging"),VLOOKUP(C93,Products!$A$2:$C$8,3,FALSE),0) -> 0
A94: AJIPJP75 | B94: Marty Freudenburg | C94: GTX Plus Basic | D94: Codehow | E94: Lost | F94: 42698 | G94: 42799 | H94: 0 | I94: =IF(COUNTIF(Products!$A$2:$A$8,C94)=0,C94,"") | J94: =IF(OR(E94="Prospecting",E94="Engaging"),VLOOKUP(C94,Products!$A$2:$C$8,3,FALSE),0) -> 0
A95: NYVA2G6U | B95: Versie Hillebrand | C95: MG Special | D95: Dontechi | E95: Won | F95: 42698 | G95: 42796 | H95: 57 | I95: =IF(COUNTIF(Products!$A$2:$A$8,C95)=0,C95,"") | J95: =IF(OR(E95="Prospecting",E95="Engaging"),VLOOKUP(C95,Products!$A$2:$C$8,3,FALSE),0) -> 0
A96: FF45BXTL | B96: Vicki Laflamme | C96: MG Advanced | D96: Konex | E96: Won | F96: 42698 | G96: 42821 | H96: 3671 | I96: =IF(COUNTIF(Products!$A$2:$A$8,C96)=0,C96,"") | J96: =IF(OR(E96="Prospecting",E96="Engaging"),VLOOKUP(C96,Products!$A$2:$C$8,3,FALSE),0) -> 0
A97: TTA9LYBS | B97: Anna Snelling | C97: MG Special | D97: Treequote | E97: Won | F97: 42699 | G97: 42795 | H97: 58 | I97: =IF(COUNTIF(Products!$A$2:$A$8,C97)=0,C97,"") | J97: =IF(OR(E97="Prospecting",E97="Engaging"),VLOOKUP(C97,Products!$A$2:$C$8,3,FALSE),0) -> 0
A98: PAGZQH8L | B98: Cecily Lampkin | C98: MG Advanced | D98: Treequote | E98: Won | F98: 42699 | G98: 42800 | H98: 3956 | I98: =IF(COUNTIF(Products!$A$2:$A$8,C98)=0,C98,"") | J98: =IF(OR(E98="Prospecting",E98="Engaging"),VLOOKUP(C98,Products!$A$2:$C$8,3,FALSE),0) -> 0
A99: J7YF6DS7 | B99: Corliss Cosme | C99: GTX Plus Pro | D99: Betasoloin | E99: Won | F99: 42699 | G99: 42795 | H99: 5964 | I99: =IF(COUNTIF(Products!$A$2:$A$8,C99)=0,C99,"") | J99: =IF(OR(E99="Prospecting",E99="Engaging"),VLOOKUP(C99,Products!$A$2:$C$8,3,FALSE),0) -> 0
A100: S5IXY4Z9 | B100: Corliss Cosme | C100: GTX Pro | D100: Betasoloin | E100: Won | F100: 42699 | G100: 42800 | H100: 4570 | I100: =IF(COUNTIF(Products!$A$2:$A$8,C100)=0,C100,"") | J100: =IF(OR(E100="Prospecting",E100="Engaging"),VLOOKUP(C100,Products!$A$2:$C$8,3,FALSE),0) -> 0
A101: JQBJMETQ | B101: Darcel Schlecht | C101: MG Special | D101: Domzoom | E101: Won | F101: 42699 | G101: 42821 | H101: 49 | I101: =IF(COUNTIF(Products!$A$2:$A$8,C101)=0,C101,"") | J101: =IF(OR(E101="Prospecting",E101="Engaging"),VLOOKUP(C101,Products!$A$2:$C$8,3,FALSE),0) -> 0
A102: 0LVWSWEW | B102: Violet Mclelland | C102: MG Special | D102: Donquadtech | E102: Won | F102: 42699 | G102: 42800 | H102: 65 | I102: =IF(COUNTIF(Products!$A$2:$A$8,C102)=0,C102,"") | J102: =IF(OR(E102="Prospecting",E102="Engaging"),VLOOKUP(C102,Products!$A$2:$C$8,3,FALSE),0) -> 0
A103: K53BC1T9 | B103: Anna Snelling | C103: MG Special | D103: Domzoom | E103: Lost | F103: 42700 | G103: 42821 | H103: 0 | I103: =IF(COUNTIF(Products!$A$2:$A$8,C103)=0,C103,"") | J103: =IF(OR(E103="Prospecting",E103="Engaging"),VLOOKUP(C103,Products!$A$2:$C$8,3,FALSE),0) -> 0
A104: D40N5I9Y | B104: Darcel Schlecht | C104: GTX Pro | D104: Finhigh | E104: Won | F104: 42700 | G104: 42802 | H104: 4739 | I104: =IF(COUNTIF(Products!$A$2:$A$8,C104)=0,C104,"") | J104: =IF(OR(E104="Prospecting",E104="Engaging"),VLOOKUP(C104,Products!$A$2:$C$8,3,FALSE),0) -> 0
... A108: UK0LEZRJ | B108: Kary Hendrixson | C108: GTX Basic | D108: Condax | E108: Won | F108: 42701 | G108: 42797 | H108: 532 | I108: =IF(COUNTIF(Products!$A$2:$A$8,C108)=0,C108,"") | J108: =IF(OR(E108="Prospecting",E108="Engaging"),VLOOKUP(C108,Products!$A$2:$C$8,3,FALSE),0) -> 0
A109: PFFHM7HR | B109: Markita Hansen | C109: MG Advanced | D109: Opentech | E109: Engaging | F109: 42701 | I109: =IF(COUNTIF(Products!$A$2:$A$8,C109)=0,C109,"") | J109: =IF(OR(E109="Prospecting",E109="Engaging"),VLOOKUP(C109,Products!$A$2:$C$8,3,FALSE),0) -> 3393
...

Sheet Accounts
A1: account | B1: sector | C1: year_established | D1: revenue | E1: employees | F1: office_location | G1: subsidiary_of
A2: Acme Corporation | B2: technolgy | C2: 1996 | D2: 1100.04 | E2: 2822 | F2: United States
A3: Betasoloin | B3: medical | C3: 1999 | D3: 251.41 | E3: 495 | F3: United States
A4: Betatech | B4: medical | C4: 1986 | D4: 647.18 | E4: 1185 | F4: Kenya
A5: Bioholding | B5: medical | C5: 2012 | D5: 587.34 | E5: 1356 | F5: Philipines
A6: Bioplex | B6: medical | C6: 1991 | D6: 326.82 | E6: 1016 | F6: United States
A7: Blackzim | B7: retail | C7: 2009 | D7: 497.11 | E7: 1588 | F7: United States
A8: Bluth Company | B8: technolgy | C8: 1993 | D8: 1242.32 | E8: 3027 | F8: United States | G8: Acme Corporation
A9: Bubba Gump | B9: software | C9: 2002 | D9: 987.39 | E9: 2253 | F9: United States
A10: Cancity | B10: retail | C10: 2001 | D10: 718.62 | E10: 2448 | F10: United States
A11: Cheers | B11: entertainment | C11: 1993 | D11: 4269.9 | E11: 6472 | F11: United States | G11: Massive Dynamic
A12: Codehow | B12: software | C12: 1998 | D12: 2714.9 | E12: 2641 | F12: United States | G12: Acme Corporation
A13: Condax | B13: medical | C13: 2017 | D13: 4.54 | E13: 9 | F13: United States
A14: Conecom | B14: technolgy | C14: 2005 | D14: 1520.66 | E14: 1806 | F14: United States
A15: Dalttechnology | B15: software | C15: 2013 | D15: 98.79 | E15: 96 | F15: United States | G15: Bubba Gump
A16: dambase | B16: marketing | C16: 1995 | D16: 2173.98 | E16: 2928 | F16: United States | G16: Inity
A17: Domzoom | B17: entertainment | C17: 1998 | D17: 217.87 | E17: 551 | F17: United States
A18: Doncon | B18: technolgy | C18: 2010 | D18: 587.72 | E18: 1501 | F18: United States
A19: Donquadtech | B19: technolgy | C19: 1992 | D19: 1712.68 | E19: 3194 | F19: United States | G19: Acme Corporation
A20: Dontechi | B20: software | C20: 1982 | D20: 4618 | E20: 10083 | F20: United States
A21: Donware | B21: marketing | C21: 1999 | D21: 1197.44 | E21: 2570 | F21: United States
A22: Fasehatice | B22: retail | C22: 1990 | D22: 4968.91 | E22: 7523 | F22: United States
A23: Faxquote | B23: telecommunications | C23: 1995 | D23: 1825.82 | E23: 5595 | F23: United States | G23: Sonron
A24: Finhigh | B24: finance | C24: 2006 | D24: 1102.43 | E24: 1759 | F24: United States
A25: Finjob | B25: employment | C25: 1988 | D25: 2059.9 | E25: 3644 | F25: United States
A26: Funholding | B26: finance | C26: 1991 | D26: 2819.5 | E26: 7227 | F26: United States | G26: Golddex
A27: Ganjaflex | B27: retail | C27: 1995 | D27: 5158.71 | E27: 17479 | F27: Japan
A28: Gekko & Co | B28: retail | C28: 1990 | D28: 2520.83 | E28: 3502 | F28: United States
A29: Genco Pura Olive Oil Company | B29: retail | C29: 2007 | D29: 894.33 | E29: 1635 | F29: Italy
A30: Globex Corporation | B30: technolgy | C30: 2000 | D30: 1223.72 | E30: 2497 | F30: Norway
A31: Gogozoom | B31: telecommunications | C31: 2007 | D31: 86.68 | E31: 187 | F31: United States | G31: Sonron
A32: Golddex | B32: finance | C32: 2008 | D32: 52.5 | E32: 165 | F32: United States
A33: Goodsilron | B33: marketing | C33: 2000 | D33: 2952.73 | E33: 5107 | F33: United States
A34: Green-Plus | B34: services | C34: 2003 | D34: 692.19 | E34: 1922 | F34: United States
A35: Groovestreet | B35: retail | C35: 2003 | D35: 223.8 | E35: 299 | F35: United States
A36: Hatfan | B36: services | C36: 1982 | D36: 792.46 | E36: 1299 | F36: United States
A37: Hottechi | B37: technolgy | C37: 1997 | D37: 8170.38 | E37: 16499 | F37: Korea
A38: Initech | B38: telecommunications | C38: 1994 | D38: 6395.05 | E38: 20275 | F38: United States
A39: Inity | B39: marketing | C39: 1986 | D39: 2403.58 | E39: 8801 | F39: United States
A40: Isdom | B40: medical | C40: 2002 | D40: 3178.24 | E40: 4540 | F40: United States
A41: Iselectrics | B41: technolgy | C41: 2011 | D41: 527.11 | E41: 1428 | F41: United States | G41: Acme Corporation
A42: J-Texon | B42: retail | C42: 1989 | D42: 1388.67 | E42: 3583 | F42: United States
A43: Kan-code | B43: software | C43: 1982 | D43: 11698.03 | E43: 34288 | F43: United States
A44: Kinnamplus | B44: retail | C44: 2004 | D44: 702.72 | E44: 1831 | F44: United States
A45: Konex | B45: technolgy | C45: 1980 | D45: 7708.38 | E45: 13756 | F45: United States
A46: Konmatfix | B46: marketing | C46: 1985 | D46: 375.43 | E46: 1190 | F46: United States
A47: Labdrill | B47: medical | C47: 1985 | D47: 2741.37 | E47: 9226 | F47: United States
A48: Lexiqvolax | B48: medical | C48: 2004 | D48: 1618.89 | E48: 3889 | F48: United States
A49: Massive Dynamic | B49: entertainment | C49: 1989 | D49: 665.06 | E49: 1095 | F49: United States
A50: Mathtouch | B50: marketing | C50: 1984 | D50: 3027.46 | E50: 9516 | F50: Jordan
A51: Nam-zim | B51: services | C51: 1987 | D51: 405.59 | E51: 1179 | F51: Brazil | G51: Warephase
A52: Newex | B52: services | C52: 1991 | D52: 1012.72 | E52: 3492 | F52: Germany
A53: Ontomedia | B53: employment | C53: 1997 | D53: 882.12 | E53: 2769 | F53: United States
A54: Opentech | B54: finance | C54: 1994 | D54: 355.23 | E54: 853 | F54: United States
A55: Plexzap | B55: retail | C55: 2001 | D55: 2437.85 | E55: 4874 | F55: United States
A56: Plusstrip | B56: entertainment | C56: 2002 | D56: 349.81 | E56: 315 | F56: United States
A57: Plussunin | B57: retail | C57: 2003 | D57: 1419.98 | E57: 4018 | F57: United States
A58: Rangreen | B58: technolgy | C58: 1987 | D58: 2938.67 | E58: 8775 | F58: Panama
A59: Rantouch | B59: telecommunications | C59: 1994 | D59: 1188.42 | E59: 3015 | F59: United States
A60: Ron-tech | B60: medical | C60: 1992 | D60: 3922.42 | E60: 6837 | F60: United States
A61: Rundofase | B61: technolgy | C61: 1983 | D61: 1008.06 | E61: 1238 | F61: United States
A62: Scotfind | B62: software | C62: 1996 | D62: 6354.87 | E62: 16780 | F62: United States | G62: Bubba Gump
A63: Scottech | B63: marketing | C63: 2012 | D63: 45.39 | E63: 100 | F63: United States | G63: Inity
A64: Silis | B64: medical | C64: 1994 | D64: 2818.38 | E64: 6290 | F64: United States
A65: Singletechno | B65: retail | C65: 1996 | D65: 2214.94 | E65: 5374 | F65: United States
A66: Sonron | B66: telecommunications | C66: 1999 | D66: 1699.85 | E66: 5108 | F66: United States
A67: Stanredtax | B67: finance | C67: 1987 | D67: 1698.2 | E67: 3798 | F67: United States
A68: Statholdings | B68: employment | C68: 1997 | D68: 291.27 | E68: 586 | F68: United States
A69: Streethex | B69: retail | C69: 1988 | D69: 1376.8 | E69: 1165 | F69: Belgium
A70: Sumace | B70: retail | C70: 2000 | D70: 167.89 | E70: 493 | F70: Romania
A71: Sunnamplex | B71: marketing | C71: 2008 | D71: 894.37 | E71: 1593 | F71: Poland
A72: The New York Inquirer | B72: medical | C72: 1996 | D72: 439.21 | E72: 792 | F72: United States
A73: Toughzap | B73: retail | C73: 1995 | D73: 332.43 | E73: 799 | F73: United States
A74: Treequote | B74: telecommunications | C74: 1988 | D74: 5266.09 | E74: 8595 | F74: United States | G74: Sonron
A75: Umbrella Corporation | B75: finance | C75: 1998 | D75: 2022.14 | E75: 5113 | F75: United States
A76: Vehement Capital Partners | B76: finance | C76: 1993 | D76: 646.1 | E76: 883 | F76: United States | G76: Golddex
A77: Warephase | B77: services | C77: 1997 | D77: 2041.73 | E77: 5276 | F77: United States
A78: Xx-holding | B78: finance | C78: 1993 | D78: 7537.24 | E78: 20293 | F78: United States
A79: Xx-zobam | B79: entertainment | C79: 1989 | D79: 3838.39 | E79: 8274 | F79: United States
A80: Y-corporation | B80: employment | C80: 1983 | D80: 2871.35 | E80: 9561 | F80: United States
A81: Yearin | B81: retail | C81: 2005 | D81: 2261.05 | E81: 3851 | F81: United States
A82: Zathunicon | B82: retail | C82: 2010 | D82: 71.12 | E82: 144 | F82: United States
A83: Zencorporation | B83: technolgy | C83: 2011 | D83: 40.79 | E83: 142 | F83: China
A84: Zoomit | B84: entertainment | C84: 1992 | D84: 324.19 | E84: 978 | F84: United States
A85: Zotware | B85: software | C85: 1979 | D85: 4478.47 | E85: 13809 | F85: United States
A86: Zumgoity | B86: medical | C86: 1984 | D86: 441.08 | E86: 1210 | F86: United States

Sheet Sales_teams
A1: sales_agent | B1: manager | C1: regional_office
A2: Anna Snelling | B2: Dustin Brinkmann | C2: Central
A3: Cecily Lampkin | B3: Dustin Brinkmann | C3: Central
A4: Versie Hillebrand | B4: Dustin Brinkmann | C4: Central
A5: Lajuana Vencill | B5: Dustin Brinkmann | C5: Central
A6: Moses Frase | B6: Dustin Brinkmann | C6: Central
A7: Jonathan Berthelot | B7: Melvin Marxen | C7: Central
A8: Marty Freudenburg | B8: Melvin Marxen | C8: Central
A9: Gladys Colclough | B9: Melvin Marxen | C9: Central
A10: Niesha Huffines | B10: Melvin Marxen | C10: Central
A11: Darcel Schlecht | B11: Melvin Marxen | C11: Central
A12: Mei-Mei Johns | B12: Melvin Marxen | C12: Central
... A36: Carl Lin | B36: Summer Sewald | C36: West

Sheet Products
A1: product | B1: series | C1: sales_price
A2: GTX Basic | B2: GTX | C2: 550
A3: GTX Pro | B3: GTX | C3: 4821
A4: MG Special | B4: MG | C4: 55
A5: MG Advanced | B5: MG | C5: 3393
A6: GTX Plus Pro | B6: GTX | C6: 5482
A7: GTX Plus Basic | B7: GTX | C7: 1096
A8: GTK 500 | B8: GTK | C8: 26768
